pythonbytes/__init__.py
pythonbytes/download.py
pythonbytes-0.1.3.dist-info/WHEEL
pythonbytes-0.1.3.dist-info/METADATA
pythonbytes-0.1.3.dist-info/RECORD
